pytest_snapshot/__init__.py
pytest_snapshot/_utils.py
pytest_snapshot/_version.py
pytest_snapshot/plugin.py
pytest_snapshot_with_message_generator-0.0.1.dist-info/LICENSE
pytest_snapshot_with_message_generator-0.0.1.dist-info/METADATA
pytest_snapshot_with_message_generator-0.0.1.dist-info/WHEEL
pytest_snapshot_with_message_generator-0.0.1.dist-info/entry_points.txt
pytest_snapshot_with_message_generator-0.0.1.dist-info/top_level.txt
pytest_snapshot_with_message_generator-0.0.1.dist-info/RECORD
