Metadata-Version: 2.1
Name: pytest-snapshot-with-message-generator
Version: 0.0.1
Summary: A plugin for snapshot testing with pytest.
Home-page: https://github.com/pamelafox/pytest-snapshot
Author: Joseph Roitman
Author-email: joseph.roitman@gmail.com
Maintainer: Pamela Fox
Maintainer-email: pamela.fox@gmail.com
License: MIT
Classifier: Development Status :: 4 - Beta
Classifier: Framework :: Pytest
Classifier: Intended Audience :: Developers
Classifier: Topic :: Software Development :: Testing
Classifier: Programming Language :: Python
Classifier: Programming Language :: Python :: 3
Classifier: Programming Language :: Python :: 3.5
Classifier: Programming Language :: Python :: 3.6
Classifier: Programming Language :: Python :: 3.7
Classifier: Programming Language :: Python :: 3.8
Classifier: Programming Language :: Python :: 3.9
Classifier: Programming Language :: Python :: 3.10
Classifier: Programming Language :: Python :: Implementation :: CPython
Classifier: Programming Language :: Python :: Implementation :: PyPy
Classifier: Operating System :: OS Independent
Classifier: License :: OSI Approved :: MIT License
Requires-Python: >=3.5
License-File: LICENSE
Requires-Dist: pytest (>=3.0.0)
